vmware_aria_operations_integration_sdk/__init__.py
vmware_aria_operations_integration_sdk/adapter_configurations/__init__.py
vmware_aria_operations_integration_sdk/adapter_configurations/adapter_config.py
vmware_aria_operations_integration_sdk/adapter_configurations/adapter_templates/__init__.py
vmware_aria_operations_integration_sdk/adapter_configurations/adapter_templates/__pycache__/__init__.cpython-310.pyc
vmware_aria_operations_integration_sdk/adapter_configurations/adapter_templates/java/__init__.py
vmware_aria_operations_integration_sdk/adapter_configurations/adapter_templates/java/__pycache__/__init__.cpython-310.pyc
vmware_aria_operations_integration_sdk/adapter_configurations/adapter_templates/java/__pycache__/java_adapter.cpython-310.pyc
vmware_aria_operations_integration_sdk/adapter_configurations/adapter_templates/java/java_adapter.py
vmware_aria_operations_integration_sdk/adapter_configurations/adapter_templates/java/new_adapter/build.gradle.kts.template
vmware_aria_operations_integration_sdk/adapter_configurations/adapter_templates/java/new_adapter/src/main/java/Adapter.java.template
vmware_aria_operations_integration_sdk/adapter_configurations/adapter_templates/java/sample_adapter/build.gradle.kts.template
vmware_aria_operations_integration_sdk/adapter_configurations/adapter_templates/java/sample_adapter/src/main/java/Adapter.java.template
vmware_aria_operations_integration_sdk/adapter_configurations/adapter_templates/python/__init__.py
vmware_aria_operations_integration_sdk/adapter_configurations/adapter_templates/python/__pycache__/__init__.cpython-310.pyc
vmware_aria_operations_integration_sdk/adapter_configurations/adapter_templates/python/__pycache__/python_adapter.cpython-310.pyc
vmware_aria_operations_integration_sdk/adapter_configurations/adapter_templates/python/new_adapter/adapter_requirements.txt
vmware_aria_operations_integration_sdk/adapter_configurations/adapter_templates/python/new_adapter/app/adapter.py.template
vmware_aria_operations_integration_sdk-1.2.0.dist-info/LICENSE
vmware_aria_operations_integration_sdk-1.2.0.dist-info/METADATA
vmware_aria_operations_integration_sdk-1.2.0.dist-info/NOTICE
vmware_aria_operations_integration_sdk-1.2.0.dist-info/WHEEL
vmware_aria_operations_integration_sdk-1.2.0.dist-info/entry_points.txt
vmware_aria_operations_integration_sdk-1.2.0.dist-info/RECORD
