Metadata-Version: 2.3
Name: vmware_aria_operations_integration_sdk
Version: 1.2.0
Summary: A set of tools to help users create, test, and build containerized management packs for VMware Aria Operations
License: Apache-2.0
Author: Kyle Rokos
Author-email: kyle.rokos@broadcom.com
Requires-Python: >=3.9,<3.13
Classifier: License :: OSI Approved :: Apache Software License
Classifier: Programming Language :: Python :: 3
Classifier: Programming Language :: Python :: 3.9
Classifier: Programming Language :: Python :: 3.10
Classifier: Programming Language :: Python :: 3.11
Classifier: Programming Language :: Python :: 3.12
Requires-Dist: GitPython (>=3.1.30,<4.0.0)
Requires-Dist: aenum (>=3.1.11,<4.0.0)
Requires-Dist: docker (>=7.1.0,<8.0.0)
Requires-Dist: httpx (>=0.23.0,<0.24.0)
Requires-Dist: importlib-metadata (>=5.0.0,<6.0.0)
Requires-Dist: importlib-resources (>=5.10.0,<6.0.0)
Requires-Dist: jsonschema-spec (>=0.1.2,<0.2.0)
Requires-Dist: lxml (>=4.9.2,<5.0.0)
Requires-Dist: openapi-core (>=0.15.0,<0.16.0)
Requires-Dist: openapi-schema-validator (>=0.2.3,<0.3.0)
Requires-Dist: openapi-spec-validator (>=0.4.0,<0.5.0)
Requires-Dist: pillow (>=9.3,<11.0)
Requires-Dist: prompt-toolkit (>=3.0.29,<4.0.0)
Requires-Dist: sen (>=0.6.2,<0.7.0)
Requires-Dist: validators (>=0.20.0,<0.21.0)
Requires-Dist: vmware-aria-operations-integration-sdk-lib (>=1.0.0,<2.0.0)
Requires-Dist: xmlschema (<2.5.0)
Project-URL: Repository, https://github.com/vmware/vrealize-operations-integration-sdk
